screenoverlay/__init__.py
screenoverlay/overlay.py
screenoverlay-0.6.3.dist-info/licenses/LICENSE
screenoverlay-0.6.3.dist-info/METADATA
screenoverlay-0.6.3.dist-info/WHEEL
screenoverlay-0.6.3.dist-info/top_level.txt
screenoverlay-0.6.3.dist-info/RECORD
